stonks/__init__.py
stonks/plugin.py
stonks/stonks.py
stonks/plugins/__init__.py
stonks/plugins/base.py
stonks_data-0.0.1.dist-info/LICENSE
stonks_data-0.0.1.dist-info/METADATA
stonks_data-0.0.1.dist-info/WHEEL
stonks_data-0.0.1.dist-info/top_level.txt
stonks_data-0.0.1.dist-info/RECORD
