Metadata-Version: 2.1
Name: stonks-data
Version: 0.0.1
Summary: A python package for accessing historical stock data. This library was designed with a plugin framework for easy extendability and the data can optionally be stored in a local cache for quicker access.
Home-page: https://github.com/JVH-Software/Stonks
Author: Justin van Heek
Author-email: justin.vanheek@vhsoftware.dev
License: UNKNOWN
Platform: UNKNOWN
Classifier: Programming Language :: Python :: 3
Classifier: License :: OSI Approved :: MIT License
Classifier: Operating System :: OS Independent
Requires-Python: >=3.6
